omnimancer/__init__.py
omnimancer/__main__.py
omnimancer/cli/__init__.py
omnimancer/cli/agent_manager.py
omnimancer/cli/agent_wizard.py
omnimancer/cli/approval_formatter.py
omnimancer/cli/approval_integration.py
omnimancer/cli/approval_prompt.py
omnimancer/cli/batch_approval_display.py
omnimancer/cli/batch_approval_filters.py
omnimancer/cli/batch_operation_monitor.py
omnimancer/cli/commands.py
omnimancer/cli/completion_handler.py
omnimancer/cli/config_setup_wizard.py
omnimancer/cli/dynamic_commands.py
omnimancer/cli/interface.py
omnimancer/cli/performance_dashboard.py
omnimancer/cli/commands/performance_cmd.py
omnimancer/cli/handlers/__init__.py
omnimancer/cli/handlers/agent_handler.py
omnimancer/cli/handlers/agent_persona_handler.py
omnimancer/cli/handlers/custom_agent_handler.py
omnimancer/cli/handlers/permissions_handler.py
omnimancer/core/__init__.py
omnimancer/core/agent_engine.py
omnimancer/core/agent_mode_manager.py
omnimancer/core/agent_progress_ui.py
omnimancer/core/chat_manager.py
omnimancer/core/config_manager.py
omnimancer/core/config_migration.py
omnimancer/core/config_provider.py
omnimancer/core/config_security_validator.py
omnimancer/core/config_validator.py
omnimancer/core/conversation_manager.py
omnimancer/core/engine.py
omnimancer/core/enhanced_input.py
omnimancer/core/env_loader.py
omnimancer/core/fallback_manager.py
omnimancer/core/health_monitor.py
omnimancer/core/history_manager.py
omnimancer/core/mcp_integration_layer.py
omnimancer/core/models.py
omnimancer/core/provider_capabilities.py
omnimancer/core/provider_initializer.py
omnimancer/core/provider_registry.py
omnimancer/core/setup_wizard.py
omnimancer/core/setup_wizard_core.py
omnimancer/core/setup_wizard_guide_generator.py
omnimancer/core/setup_wizard_provider_setup.py
omnimancer/core/setup_wizard_ui.py
omnimancer/core/setup_wizard_validation.py
omnimancer/core/signal_handler.py
omnimancer/core/agent/__init__.py
omnimancer/core/agent/agent_config.py
omnimancer/core/agent/agent_switcher.py
omnimancer_cli-0.1.15.dist-info/licenses/LICENSE
omnimancer_cli-0.1.15.dist-info/METADATA
omnimancer_cli-0.1.15.dist-info/WHEEL
omnimancer_cli-0.1.15.dist-info/entry_points.txt
omnimancer_cli-0.1.15.dist-info/top_level.txt
omnimancer_cli-0.1.15.dist-info/RECORD
