Metadata-Version: 2.4
Name: omnimancer-cli
Version: 0.1.15
Summary: A unified command-line interface for multiple AI language models
Author-email: Kellan Strong <kellan@jite.ai>
License: MIT
Project-URL: Homepage, https://gitlab.com/jite-ai/omnimancer
Project-URL: Repository, https://gitlab.com/jite-ai/omnimancer
Project-URL: Issues, https://gitlab.com/jite-ai/omnimancer/issues
Keywords: ai,cli,chat,openai,claude,language-model
Classifier: Development Status :: 3 - Alpha
Classifier: Intended Audience :: Developers
Classifier: License :: OSI Approved :: MIT License
Classifier: Operating System :: OS Independent
Classifier: Programming Language :: Python :: 3
Classifier: Programming Language :: Python :: 3.10
Classifier: Programming Language :: Python :: 3.11
Classifier: Programming Language :: Python :: 3.12
Classifier: Topic :: Software Development :: Libraries :: Python Modules
Classifier: Topic :: Communications :: Chat
Requires-Python: >=3.10
License-File: LICENSE
Requires-Dist: click>=8.0.0
Requires-Dist: rich>=13.0.0
Requires-Dist: httpx>=0.24.0
Requires-Dist: pydantic>=2.0.0
Requires-Dist: cryptography>=41.0.0
Requires-Dist: python-dotenv>=1.0.0
Requires-Dist: certifi>=2023.0.0
Requires-Dist: aiofiles>=23.0.0
Requires-Dist: aiohttp>=3.8.0
Requires-Dist: psutil>=5.9.0
Requires-Dist: beautifulsoup4>=4.12.0
Requires-Dist: html2text>=2020.1.16
Requires-Dist: jsonschema>=4.17.0
Requires-Dist: readability-lxml>=0.8.1
Requires-Dist: PyYAML>=6.0.0
Requires-Dist: toml>=0.10.2
Provides-Extra: dev
Requires-Dist: pytest>=7.0.0; extra == "dev"
Requires-Dist: pytest-cov>=4.0.0; extra == "dev"
Requires-Dist: pytest-asyncio>=0.21.0; extra == "dev"
Requires-Dist: pytest-mock>=3.10.0; extra == "dev"
Requires-Dist: black>=23.0.0; extra == "dev"
Requires-Dist: isort>=5.12.0; extra == "dev"
Requires-Dist: flake8>=6.0.0; extra == "dev"
Requires-Dist: mypy>=1.0.0; extra == "dev"
Dynamic: license-file
